{
  "step_number": "324",
  "review_and_appreciate": "Review and Appreciate: How well did you take care of yourself yesterday? Stay on The Path.",
  "step_of_the_day": {
    "title": "Step of the Day:\n            Pay attention to how focused you are while going through your day (Pillar #7 & 9)",
    "content": "“The key to success is doing the common things uncommonly well\\\" John D. Rockefeller, Jr.One of the dichotomies I’ve been discussing is between functioning automatically (as we usually do), versus\n            being present each moment - supporting living in a place of choice. To grow and keep improving you must be\n            able to make the choice to do or think differently from what you were taught, moment by moment.In addition to choosing how you want to be and respond; the next step is to hold the intention to do it\n            uncommonly well. To keep shooting for excellence in how you are in the world."
  },
  "action_step": "Today hold the intention to be as present as much of the time as possible, allowing for you to be in a place\n            of choice. From that place, be exceptional in your performance.",
  "journal_entry": "How important is it for you to always give 100%?"
}